simpleaexec/__init__.py
simpleaexec/do.py
simpleaexec-0.0.1.dist-info/METADATA
simpleaexec-0.0.1.dist-info/WHEEL
simpleaexec-0.0.1.dist-info/top_level.txt
simpleaexec-0.0.1.dist-info/RECORD
