Metadata-Version: 2.1
Name: simpleaexec
Version: 0.0.1
Summary: Simple async. executor.
Home-page: UNKNOWN
Author: mqchinee
Author-email: UNKNOWN
License: UNKNOWN
Keywords: python,aexec,simple
Platform: UNKNOWN
Classifier: Development Status :: 1 - Planning
Classifier: Intended Audience :: Developers
Classifier: Programming Language :: Python :: 3
Classifier: Operating System :: Unix
Classifier: Operating System :: MacOS :: MacOS X
Classifier: Operating System :: Microsoft :: Windows
Requires-Dist: io
Requires-Dist: contextlib
Requires-Dist: aioconsole
